photokit/__init__.py
photokit/album.py
photokit/asset.py
photokit/changeobserver.py
photokit/constants.py
photokit/exceptions.py
photokit/fileutil.py
photokit/imageconverter.py
photokit/keyword.py
photokit/objc_utils.py
photokit/photolibrary.py
photokit/photosdb.py
photokit/platform.py
photokit/scriptingbridge.py
photokit/unicode.py
photokit/uti.py
photokit/utils.py
photokit-0.2.1.dist-info/LICENSE
photokit-0.2.1.dist-info/WHEEL
photokit-0.2.1.dist-info/METADATA
photokit-0.2.1.dist-info/RECORD
