Metadata-Version: 2.1
Name: photokit
Version: 0.2.1
Summary: Python package for accessing the macOS Photos.app library via Apple's native PhotoKit framework.
Author-email: Rhet Turnbull <rturnbull+git@gmail.com>
Requires-Python: >=3.9
Classifier: Development Status :: 2 - Pre-Alpha
Classifier: Environment :: MacOS X
Classifier: Intended Audience :: Developers
Classifier: License :: OSI Approved :: MIT License
Classifier: Operating System :: MacOS
Classifier: Programming Language :: Objective C
Classifier: Programming Language :: Python :: 3.10
Classifier: Programming Language :: Python :: 3.11
Classifier: Programming Language :: Python :: 3.9
Requires-Dist: pyobjc-core>=9.2,<11.0
Requires-Dist: pyobjc-framework-AVFoundation>=9.2,<11.0
Requires-Dist: pyobjc-framework-AppleScriptKit>=9.2,<11.0
Requires-Dist: pyobjc-framework-AppleScriptObjC>=9.2,<11.0
Requires-Dist: pyobjc-framework-Cocoa>=9.2,<11.0
Requires-Dist: pyobjc-framework-CoreServices>=9.2,<11.0
Requires-Dist: pyobjc-framework-Metal>=9.2,<11.0
Requires-Dist: pyobjc-framework-Photos>=9.2,<11.0
Requires-Dist: pyobjc-framework-Vision>=9.2,<11.0
Requires-Dist: pyobjc-framework-ScriptingBridge>=9.2,<11.0
Requires-Dist: wurlitzer>=3.0.3,<4.0.0
Requires-Dist: bump-my-version ; extra == "dev"
Requires-Dist: mkdocs>=1.4.2 ; extra == "docs"
Requires-Dist: mkdocs-material>=9.0.13 ; extra == "docs"
Requires-Dist: mkdocstrings-python>=0.8.3 ; extra == "docs"
Requires-Dist: pytest>=7.4.2 ; extra == "test"
Requires-Dist: pytest-cov ; extra == "test"
Requires-Dist: osxphotos>=0.63.4 ; extra == "test"
Project-URL: Home, https://github.com/RhetTbull/photokit
Project-URL: Issues, https://github.com/RhetTbull/photokit/issues
Project-URL: Source, https://github.com/RhetTbull/photokit
Provides-Extra: dev
Provides-Extra: docs
Provides-Extra: test
